{"entries":[{"playerName":"rumrumer1337","playerDisplayName":"rumrumer1337","prefix":"ꔨ \u00267","suffix":"","playerID":"93c912a2-3581-36ce-9e74-e03d4d14aa97","position":1,"board":"statistic_time_played","type":"DAILY","score":241.0},{"playerName":"peygorno_XxX","playerDisplayName":"peygorno_XxX","prefix":"ꔨ \u00267","suffix":"","playerID":"949fcdd0-d104-3013-a640-4c123db33aa2","position":2,"board":"statistic_time_played","type":"DAILY","score":241.0},{"playerName":"naruto_woman1","playerDisplayName":"naruto_woman1","prefix":"ꔲ \u00267","suffix":"","playerID":"66dfd515-a93a-3275-93ce-ab2be54dbd3b","position":3,"board":"statistic_time_played","type":"DAILY","score":241.0},{"playerName":"mashanaswag","playerDisplayName":"mashanaswag","prefix":"ꔨ \u00267","suffix":"","playerID":"0dc5eec9-91e4-3a3d-aff7-0393c4db2793","position":4,"board":"statistic_time_played","type":"DAILY","score":241.0},{"playerName":"fispiska","playerDisplayName":"fispiska","prefix":"ꔨ \u00267","suffix":"","playerID":"ec97619c-1e1f-3342-9468-f74be5872cff","position":5,"board":"statistic_time_played","type":"DAILY","score":241.0},{"playerName":"Montajor_YT","playerDisplayName":"Montajor_YT","prefix":"ꕀ \u00267","suffix":"","playerID":"e21498a4-5dc9-3bac-8155-397f58c3c584","position":6,"board":"statistic_time_played","type":"DAILY","score":241.0},{"playerName":"KpyIIIuTeJlb","playerDisplayName":"KpyIIIuTeJlb","prefix":"ꔨ \u00267","suffix":"","playerID":"f9e53ae2-da57-3a6c-96b2-3c0b5a38773e","position":7,"board":"statistic_time_played","type":"DAILY","score":241.0},{"playerName":"Juqym","playerDisplayName":"Juqym","prefix":"ꕒ \u00267","suffix":"","playerID":"b6340681-cdfd-3ed2-8103-969b76b0b0a2","position":8,"board":"statistic_time_played","type":"DAILY","score":241.0},{"playerName":"Jaggernaut","playerDisplayName":"Jaggernaut","prefix":"ꔨ \u00267","suffix":"","playerID":"58cb86ea-14ee-3dae-8d56-49ed731af15a","position":9,"board":"statistic_time_played","type":"DAILY","score":241.0},{"playerName":"Adelina","playerDisplayName":"Adelina","prefix":"ꔨ \u00267","suffix":"","playerID":"b66c2b32-1fa5-3963-a848-6d8aeb8b7c4c","position":10,"board":"statistic_time_played","type":"DAILY","score":241.0}],"meta":{"time":1749330256510,"type":"DAILY","board":"statistic_time_played"}}