{"entries":[{"playerName":"NeZeRiT228","playerDisplayName":"§oSosiska§r","prefix":"ꕠ \u00267","suffix":"","playerID":"10f58c60-96ca-35b6-a7b5-95bff97aaf98","position":1,"board":"statistic_player_kills","type":"DAILY","score":3021.0},{"playerName":"VVAMPIRR","playerDisplayName":"VVAMPIRR","prefix":"ꔅ \u00267","suffix":"","playerID":"f9a66cfc-bfcc-36af-b4cd-40caf4c84079","position":2,"board":"statistic_player_kills","type":"DAILY","score":156.0},{"playerName":"kuboeb2","playerDisplayName":"kuboeb2","prefix":"ꔨ \u00267","suffix":"","playerID":"c1f92eac-8751-36b1-a865-1de7204b29a9","position":3,"board":"statistic_player_kills","type":"DAILY","score":87.0},{"playerName":"Sosaldo","playerDisplayName":"Sosaldo","prefix":"ꔨ \u00267","suffix":"","playerID":"0e478106-c44a-3242-bb05-ddb21f893511","position":4,"board":"statistic_player_kills","type":"DAILY","score":82.0},{"playerName":"lubly_MATb","playerDisplayName":"lubly_MATb","prefix":"ꔨ \u00267","suffix":"","playerID":"862bf31d-a8e3-3919-9470-ae009e4cba62","position":5,"board":"statistic_player_kills","type":"DAILY","score":72.0},{"playerName":"__Mango__","playerDisplayName":"__Mango__","prefix":"ꕠ \u00267","suffix":"","playerID":"6a603675-5645-37a4-8373-dc9f1d54a579","position":6,"board":"statistic_player_kills","type":"DAILY","score":65.0},{"playerName":"Future0222","playerDisplayName":"§oAueroFlote§r","prefix":"ꕀ \u00267","suffix":"","playerID":"5f3a2dcf-d28a-316c-9ec2-6c3e92bc2033","position":7,"board":"statistic_player_kills","type":"DAILY","score":63.0},{"playerName":"CPacketGay_YT","playerDisplayName":"§oakvi4§r","prefix":"ꔨ \u00267","suffix":"","playerID":"8612575d-5740-3c9e-8777-e4091cf1bb3d","position":8,"board":"statistic_player_kills","type":"DAILY","score":57.0},{"playerName":"Genij_igry","playerDisplayName":"Genij_igry","prefix":"ꔨ \u00267","suffix":"","playerID":"81edf4c8-52fb-3114-bf07-9be250c53bcd","position":9,"board":"statistic_player_kills","type":"DAILY","score":54.0},{"playerName":"Arm0bka","playerDisplayName":"Arm0bka","prefix":"ꔲ \u00267","suffix":"","playerID":"353397fe-904d-342a-bf4d-9ba5bae2491a","position":10,"board":"statistic_player_kills","type":"DAILY","score":54.0}],"meta":{"time":1750280405101,"type":"DAILY","board":"statistic_player_kills"}}