{"entries":[{"playerName":"Drakula","playerDisplayName":"Drakula","prefix":"§x§F§B§9§C§0§8§lW§x§F§B§A§E§0§8§lI§x§F§B§B§F§0§8§lN§x§F§B§D§1§0§8§lN§x§F§B§E§2§0§8§lE§x§F§B§F§4§0§8§lR\u00267 ","suffix":"","playerID":"b6da5282-f5dd-3edd-9e7d-d4c5c648d0a6","position":1,"board":"vault_eco_balance_commas","type":"DAILY","score":1.4887593E7},{"playerName":"maksSASS","playerDisplayName":"maksSASS","prefix":"\u00260\u0026r\u0026x\u0026F\u0026F\u00261\u00260\u00261\u00260\u0026lY\u0026f\u0026lT§6§l+ §7","suffix":"","playerID":"73916a6a-0aca-32dd-9049-fb85c39e5a27","position":2,"board":"vault_eco_balance_commas","type":"DAILY","score":4282249.0},{"playerName":"Ender_Life2","playerDisplayName":"Ender_Life2","prefix":"\u0026x\u0026C\u0026B\u0026C\u0026B\u0026C\u0026B\u0026lR\u0026x\u0026D\u00265\u0026D\u00265\u0026D\u00265\u0026lA\u0026x\u0026E\u00260\u0026E\u00260\u0026E\u00260\u0026lB\u0026x\u0026E\u0026A\u0026E\u0026A\u0026E\u0026A\u0026lB\u0026x\u0026F\u00265\u0026F\u00265\u0026F\u00265\u0026lI\u0026x\u0026F\u0026F\u0026F\u0026F\u0026F\u0026F\u0026lT§6§l+ §7","suffix":"","playerID":"d991a4e7-76bd-3413-81f9-7410650b7beb","position":3,"board":"vault_eco_balance_commas","type":"DAILY","score":3788923.0},{"playerName":"_PaRadox__","playerDisplayName":"§oXdeadForChina§r","prefix":"\u0026x\u0026C\u0026B\u0026C\u0026B\u0026C\u0026B\u0026lR\u0026x\u0026D\u00265\u0026D\u00265\u0026D\u00265\u0026lA\u0026x\u0026E\u00260\u0026E\u00260\u0026E\u00260\u0026lB\u0026x\u0026E\u0026A\u0026E\u0026A\u0026E\u0026A\u0026lB\u0026x\u0026F\u00265\u0026F\u00265\u0026F\u00265\u0026lI\u0026x\u0026F\u0026F\u0026F\u0026F\u0026F\u0026F\u0026lT§6§l+ §7","suffix":"","playerID":"69a7e571-2963-3a25-8dce-03fffc8bdc00","position":4,"board":"vault_eco_balance_commas","type":"DAILY","score":3066642.0},{"playerName":"kukusaka","playerDisplayName":"§o4uHa3ec§r","prefix":"\u0026x\u0026C\u0026B\u0026C\u0026B\u0026C\u0026B\u0026lR\u0026x\u0026D\u00265\u0026D\u00265\u0026D\u00265\u0026lA\u0026x\u0026E\u00260\u0026E\u00260\u0026E\u00260\u0026lB\u0026x\u0026E\u0026A\u0026E\u0026A\u0026E\u0026A\u0026lB\u0026x\u0026F\u00265\u0026F\u00265\u0026F\u00265\u0026lI\u0026x\u0026F\u0026F\u0026F\u0026F\u0026F\u0026F\u0026lT§6§l+ §7","suffix":"","playerID":"0eaad5dc-4948-363b-a0a8-63ac293c46ff","position":5,"board":"vault_eco_balance_commas","type":"DAILY","score":2529523.0},{"playerName":"New_History","playerDisplayName":"New_History","prefix":"§x§F§B§9§C§0§8§lW§x§F§B§A§E§0§8§lI§x§F§B§B§F§0§8§lN§x§F§B§D§1§0§8§lN§x§F§B§E§2§0§8§lE§x§F§B§F§4§0§8§lR§6§l+ §7","suffix":"","playerID":"8ec2b50e-8411-3a2f-80cf-147ce4c3261c","position":6,"board":"vault_eco_balance_commas","type":"DAILY","score":2174554.0},{"playerName":"DevRell","playerDisplayName":"§ogtx1050ti§r","prefix":"\u0026e\u0026lD.HELPER §7","suffix":"","playerID":"af73bec9-a7f8-302a-95ac-e4460b274428","position":7,"board":"vault_eco_balance_commas","type":"DAILY","score":1777752.0},{"playerName":"Zlayes","playerDisplayName":"Zlayes","prefix":"§x§F§B§9§C§0§8§lW§x§F§B§A§E§0§8§lI§x§F§B§B§F§0§8§lN§x§F§B§D§1§0§8§lN§x§F§B§E§2§0§8§lE§x§F§B§F§4§0§8§lR§6§l+ §7","suffix":"","playerID":"514cae18-f92d-32e9-bc9a-126bf93fd944","position":8,"board":"vault_eco_balance_commas","type":"DAILY","score":1535017.0},{"playerName":"TIP4IK","playerDisplayName":"TIP4IK","prefix":"\u00260\u0026r\u0026x\u0026F\u0026F\u00261\u00260\u00261\u00260\u0026lY\u0026f\u0026lT§6§l+ §7","suffix":"","playerID":"6e31c5b4-c5c8-3a89-8395-df422f197736","position":9,"board":"vault_eco_balance_commas","type":"DAILY","score":1500000.0},{"playerName":"HEPBbI","playerDisplayName":"§ouKilledByHEPBbI§r","prefix":"\u0026x\u0026C\u0026B\u0026C\u0026B\u0026C\u0026B\u0026lR\u0026x\u0026D\u00265\u0026D\u00265\u0026D\u00265\u0026lA\u0026x\u0026E\u00260\u0026E\u00260\u0026E\u00260\u0026lB\u0026x\u0026E\u0026A\u0026E\u0026A\u0026E\u0026A\u0026lB\u0026x\u0026F\u00265\u0026F\u00265\u0026F\u00265\u0026lI\u0026x\u0026F\u0026F\u0026F\u0026F\u0026F\u0026F\u0026lT§6§l+ §7","suffix":"","playerID":"39cbc9ad-f938-3022-b54d-e38e7d472e8d","position":10,"board":"vault_eco_balance_commas","type":"DAILY","score":1392000.0}],"meta":{"time":1730754000315,"type":"DAILY","board":"vault_eco_balance_commas"}}