{"entries":[{"playerName":"Gojo_Satory_","playerDisplayName":"§o0_v_pvp§r","prefix":"ꕒ \u00267","suffix":"","playerID":"21f62f73-f883-3617-b1f4-469d9a279e5e","position":1,"board":"vault_eco_balance_commas","type":"DAILY","score":2.5320466E8},{"playerName":"BMF1","playerDisplayName":"§oBMFI§r","prefix":"ꕈ \u00267","suffix":"","playerID":"61988312-e355-375e-9272-4edf9103d700","position":2,"board":"vault_eco_balance_commas","type":"DAILY","score":4.1895207E7},{"playerName":"MrKostyan","playerDisplayName":"MrKostyan","prefix":"ꕀ \u00267","suffix":"","playerID":"840dd9a8-1b6a-3722-bf58-282392bf7605","position":3,"board":"vault_eco_balance_commas","type":"DAILY","score":2.3298104E7},{"playerName":"tvinkkredzek1","playerDisplayName":"tvinkkredzek1","prefix":"ꕠ \u00267","suffix":"","playerID":"9136b6cd-4095-3a44-94bf-c3d947b45f07","position":4,"board":"vault_eco_balance_commas","type":"DAILY","score":1.0425744E7},{"playerName":"RobinZON33","playerDisplayName":"RobinZON33","prefix":"ꕒ \u00267","suffix":"","playerID":"31878b5a-6b57-33a0-a2cc-4564b5e89318","position":5,"board":"vault_eco_balance_commas","type":"DAILY","score":1.0173816E7},{"playerName":"Tobak","playerDisplayName":"§oXyligan§r","prefix":"ꕗ \u00267","suffix":"\u0026a\u0026l","playerID":"4f1ab3b6-aceb-3f0a-9632-c8fbb083f857","position":6,"board":"vault_eco_balance_commas","type":"DAILY","score":2764789.0},{"playerName":"jg84gtgg","playerDisplayName":"jg84gtgg","prefix":"ꔨ \u00267","suffix":"","playerID":"24d0556c-0477-34f2-8bf4-ebd14d328285","position":7,"board":"vault_eco_balance_commas","type":"DAILY","score":2061288.0},{"playerName":"AsTRoKENT","playerDisplayName":"§onefifes§r","prefix":"ꕗ \u00267","suffix":"\u0026a\u0026l","playerID":"82f0e386-2bf4-37e2-b305-37725840cfa4","position":8,"board":"vault_eco_balance_commas","type":"DAILY","score":1840396.0},{"playerName":"_ARTEM_VOLK_22","playerDisplayName":"_ARTEM_VOLK_22","prefix":"ꔨ \u00267","suffix":"","playerID":"bb61e896-936d-32cb-b81d-1a066f55ad1c","position":9,"board":"vault_eco_balance_commas","type":"DAILY","score":1714302.0},{"playerName":"ZxcMystiCC","playerDisplayName":"§one_datel§r","prefix":"ꕠ \u00267","suffix":"","playerID":"736e8fa4-3555-3d44-971f-5a86c4879e00","position":10,"board":"vault_eco_balance_commas","type":"DAILY","score":1400000.0}],"meta":{"time":1752008400988,"type":"DAILY","board":"vault_eco_balance_commas"}}